[
  {"question": "What does 'get your act together' mean?", "options": ["focus", "get organized", "relax"], "answer": "get organized"},
  {"question": "Meaning of 'burn bridges'?", "options": ["create conflict", "make things worse", "help people"], "answer": "create conflict"},
  {"question": "What does 'a penny for your thoughts' mean?", "options": ["ask what someone is thinking", "give money", "stay silent"], "answer": "ask what someone is thinking"},
  {"question": "Meaning of 'a leopard can't change its spots'?", "options": ["people can't change", "everyone can change", "leopards change"], "answer": "people can't change"},
  {"question": "What does 'actions speak louder than words' mean?", "options": ["actions are more important than words", "words are powerful", "both are equal"], "answer": "actions are more important than words"},
  {"question": "Meaning of 'at the drop of a hat'?", "options": ["immediately", "slowly", "after waiting"], "answer": "immediately"},
  {"question": "What does 'jump on the bandwagon' mean?", "options": ["join something popular", "start something", "avoid something"], "answer": "join something popular"},
  {"question": "Meaning of 'once in a blue moon'?", "options": ["rarely", "often", "always"], "answer": "rarely"},
  {"question": "What does 'kill two birds with one stone' mean?", "options": ["achieve two things with one effort", "hurt two people", "do two actions"], "answer": "achieve two things with one effort"},
  {"question": "Meaning of 'on the same page'?", "options": ["agree", "disagree", "be confused"], "answer": "agree"},
  {"question": "What does 'out of the blue' mean?", "options": ["unexpectedly", "predictably", "slowly"], "answer": "unexpectedly"},
  {"question": "Meaning of 'raining cats and dogs'?", "options": ["heavy rain", "light rain", "snow"], "answer": "heavy rain"}
]