[
  {"question": "Synonym of 'help'?", "options": ["assist", "ignore", "hurt"], "answer": "assist"},
  {"question": "What does 'dance' mean?", "options": ["walk", "move to music", "run"], "answer": "move to music"},
  {"question": "Opposite of 'good'?", "options": ["quick", "slow", "bad"], "answer": "bad"},
  {"question": "Synonym of 'quick'?", "options": ["rapid", "slow", "lazy"], "answer": "rapid"},
  {"question": "Opposite of 'difficult'?", "options": ["hard", "easy", "complex"], "answer": "easy"},
  {"question": "What does 'build' mean?", "options": ["destroy", "create", "ignore"], "answer": "create"},
  {"question": "What is a 'computer'?", "options": ["a tool", "an animal", "a food"], "answer": "a tool"},
  {"question": "Synonym of 'smart'?", "options": ["intelligent", "dumb", "funny"], "answer": "intelligent"},
  {"question": "Opposite of 'rich'?", "options": ["wealthy", "poor", "happy"], "answer": "poor"},
  {"question": "What does 'sleepy' mean?", "options": ["alert", "drowsy", "energetic"], "answer": "drowsy"},
  {"question": "Synonym of 'brave'?", "options": ["courageous", "scared", "calm"], "answer": "courageous"},
  {"question": "Opposite of 'empty'?", "options": ["full", "clear", "open"], "answer": "full"},
  {"question": "What is a 'bicycle'?", "options": ["a vehicle", "a building", "a tool"], "answer": "a vehicle"},
  {"question": "Synonym of 'sad' (alternative)?", "options": ["happy", "melancholy", "joyful"], "answer": "melancholy"},
  {"question": "Opposite of 'noisy'?", "options": ["quiet", "loud", "busy"], "answer": "quiet"},
  {"question": "What does 'throw' mean?", "options": ["catch", "toss", "hold"], "answer": "toss"},
  {"question": "What is a 'door'?", "options": ["something you open", "something you eat", "something you drive"], "answer": "something you open"},
  {"question": "Synonym of 'easy'?", "options": ["simple", "hard", "complex"], "answer": "simple"},
  {"question": "Opposite of 'young' (alternative)?", "options": ["old", "new", "fresh"], "answer": "old"},
  {"question": "What does 'slide' mean?", "options": ["climb", "glide", "jump"], "answer": "glide"},
  {"question": "What is a 'cup'?", "options": ["a container", "a tool", "a vehicle"], "answer": "a container"},
  {"question": "Synonym of 'clean' (alternative)?", "options": ["spotless", "dirty", "messy"], "answer": "spotless"},
  {"question": "Opposite of 'soft'?", "options": ["hard", "gentle", "smooth"], "answer": "hard"},
  {"question": "What does 'listen' mean (alternative)?", "options": ["hear", "speak", "look"], "answer": "hear"},
  {"question": "What is a 'ball'?", "options": ["a toy", "an animal", "a tool"], "answer": "a toy"},
  {"question": "Synonym of 'big' (alternative)?", "options": ["large", "tiny", "small"], "answer": "large"},
  {"question": "Opposite of 'calm'?", "options": ["agitated", "peaceful", "quiet"], "answer": "agitated"},
  {"question": "What does 'cook' mean?", "options": ["eat", "prepare food", "sing"], "answer": "prepare food"},
  {"question": "What is a 'window'?", "options": ["a door", "an opening in a wall", "a tool"], "answer": "an opening in a wall"},
  {"question": "Synonym of 'difficult'?", "options": ["challenging", "easy", "simple"], "answer": "challenging"},
  {"question": "Opposite of 'full'?", "options": ["empty", "rich", "hard"], "answer": "empty"},
  {"question": "What does 'jump' mean (alternative)?", "options": ["hop", "sit", "stand"], "answer": "hop"},
  {"question": "What is a 'pen' (alternative definition)?", "options": ["a writing tool", "an animal", "a container"], "answer": "a writing tool"},
  {"question": "Synonym of 'funny' (alternative)?", "options": ["amusing", "serious", "sad"], "answer": "amusing"},
  {"question": "Opposite of 'bright' (alternative)?", "options": ["dull", "shiny", "quiet"], "answer": "dull"}
]